tidyfinance/__init__.py
tidyfinance/_internal.py
tidyfinance/core.py
tidyfinance/data_download.py
tidyfinance/utilities.py
tidyfinance-0.2.4.dist-info/METADATA
tidyfinance-0.2.4.dist-info/WHEEL
tidyfinance-0.2.4.dist-info/licenses/LICENSE
tidyfinance-0.2.4.dist-info/RECORD
