Metadata-Version: 2.4
Name: tidyfinance
Version: 0.2.4
Summary: Tidy Finance Helper Functions
Project-URL: Repository, https://github.com/tidy-finance/py-tidyfinance
Project-URL: Issues, https://github.com/tidy-finance/py-tidyfinance/issues
Project-URL: Changelog, https://github.com/tidy-finance/py-tidyfinance/blob/master/CHANGELOG.md
Author-email: Christoph Frey <christoph.frey@gmail.com>, Christoph Scheuch <christoph@tidy-intelligence.com>
License-Expression: MIT
License-File: LICENSE
Requires-Python: >=3.10
Requires-Dist: curl-cffi>=0.10.0
Requires-Dist: dotenv>=0.9.9
Requires-Dist: lxml>=5.3.1
Requires-Dist: numpy>=1.26.0
Requires-Dist: pandas>=2.2.0
Requires-Dist: psycopg2-binary>=2.9.9
Requires-Dist: pyarrow>=19.0.1
Requires-Dist: pyyaml>=6.0.2
Requires-Dist: requests>=2.31.0
Requires-Dist: sqlalchemy>=2.0.21
Requires-Dist: statsmodels>=0.14.0
